{
  "total_downloads": 8255562,
  "mods": [
    {
      "name": "Mine Cells",
      "curseforge_id": "618790",
      "modrinth_id": "minecells",
      "curseforge_downloads": 5101866,
      "modrinth_downloads": 280593,
      "downloads": 5382459
    },
    {
      "name": "Convenient Name Tags",
      "curseforge_id": "662763",
      "modrinth_id": "convenient-name-tags",
      "curseforge_downloads": 339265,
      "modrinth_downloads": 36345,
      "downloads": 375610
    },
    {
      "name": "Convenient Decor",
      "curseforge_id": "794452",
      "modrinth_id": "convenient-decor",
      "curseforge_downloads": 2326191,
      "modrinth_downloads": 171302,
      "downloads": 2497493
    }
  ]
}