{
  "total_downloads": 3258006,
  "mods": [
    {
      "name": "Mine Cells",
      "curseforge_id": "618790",
      "modrinth_id": "minecells",
      "curseforge_downloads": 2509132,
      "modrinth_downloads": 77736,
      "downloads": 2586868
    },
    {
      "name": "Convenient Name Tags",
      "curseforge_id": "662763",
      "modrinth_id": "convenient-name-tags",
      "curseforge_downloads": 265593,
      "modrinth_downloads": 21910,
      "downloads": 287503
    },
    {
      "name": "Convenient Decor",
      "curseforge_id": "794452",
      "modrinth_id": "convenient-decor",
      "curseforge_downloads": 354485,
      "modrinth_downloads": 29150,
      "downloads": 383635
    }
  ]
}