{
  "total_downloads": 8072920,
  "mods": [
    {
      "name": "Mine Cells",
      "curseforge_id": "618790",
      "modrinth_id": "minecells",
      "curseforge_downloads": 5008115,
      "modrinth_downloads": 272463,
      "downloads": 5280578
    },
    {
      "name": "Convenient Name Tags",
      "curseforge_id": "662763",
      "modrinth_id": "convenient-name-tags",
      "curseforge_downloads": 338070,
      "modrinth_downloads": 35856,
      "downloads": 373926
    },
    {
      "name": "Convenient Decor",
      "curseforge_id": "794452",
      "modrinth_id": "convenient-decor",
      "curseforge_downloads": 2252661,
      "modrinth_downloads": 165755,
      "downloads": 2418416
    }
  ]
}