{
  "total_downloads": 24586164,
  "mods": [
    {
      "name": "Mine Cells",
      "curseforge_id": "618790",
      "modrinth_id": "minecells",
      "curseforge_downloads": 9906559,
      "modrinth_downloads": 983240,
      "downloads": 10889799
    },
    {
      "name": "Convenient Name Tags",
      "curseforge_id": "662763",
      "modrinth_id": "convenient-name-tags",
      "curseforge_downloads": 379402,
      "modrinth_downloads": 57545,
      "downloads": 436947
    },
    {
      "name": "Convenient Decor",
      "curseforge_id": "794452",
      "modrinth_id": "convenient-decor",
      "curseforge_downloads": 7328064,
      "modrinth_downloads": 761872,
      "downloads": 8089936
    },
    {
      "name": "Derelict",
      "curseforge_id": "928990",
      "modrinth_id": "derelict",
      "curseforge_downloads": 4685025,
      "modrinth_downloads": 484457,
      "downloads": 5169482
    }
  ]
}